loktar/__init__.py
loktar/check.py
loktar/cmd.py
loktar/constants.py
loktar/container.py
loktar/db.py
loktar/decorators.py
loktar/dependency.py
loktar/discovery.py
loktar/environment.py
loktar/exceptions.py
loktar/exit.py
loktar/job.py
loktar/log.py
loktar/notifications.py
loktar/parser.py
loktar/plugin.py
loktar/scm.py
loktar/serialize.py
loktar/store.py
loktar/strategy_run.py
loktar/plugins/__init__.py
loktar/plugins/artifact/__init__.py
loktar/plugins/artifact/docker.py
loktar/plugins/artifact/emr.py
loktar/plugins/artifact/jvm.py
loktar/plugins/artifact/npm.py
loktar/plugins/artifact/protobuf.py
loktar/plugins/artifact/whl.py
loktar/plugins/dependency/__init__.py
loktar/plugins/dependency/docker_compose.py
loktar/plugins/dependency/dockerfile.py
loktar/plugins/dependency/python_requirements.py
loktar/plugins/test/__init__.py
loktar/plugins/test/make.py
loktar-75.dist-info/DESCRIPTION.rst
loktar-75.dist-info/METADATA
loktar-75.dist-info/RECORD
loktar-75.dist-info/WHEEL
loktar-75.dist-info/metadata.json
loktar-75.dist-info/top_level.txt
