Metadata-Version: 2.0
Name: loktar
Version: 75
Summary: ci
Home-page: UNKNOWN
Author: Damien Goldenberg
Author-email: damdam.gold@gmail.com
License: UNKNOWN
Keywords: ci
Platform: UNKNOWN
Classifier: Development Status :: 2 - Pre-Alpha
Classifier: Natural Language :: English
Classifier: Programming Language :: Python :: 2.7
Requires-Dist: Fabric (==1.8.2)
Requires-Dist: PyGithub (==1.26.0)
Requires-Dist: boto (==2.39.0)
Requires-Dist: bravado (==8.1.2)
Requires-Dist: cffi (==1.6.0)
Requires-Dist: cryptography (==1.8.1)
Requires-Dist: docker (==2.0.2)
Requires-Dist: elasticsearch (==5.0.0)
Requires-Dist: jenkinsapi (==0.2.28)
Requires-Dist: joblib (==0.8.4)
Requires-Dist: matplotlib (==1.5.1)
Requires-Dist: networkx (==1.10)
Requires-Dist: numpy (==1.11.0)
Requires-Dist: pyaml (==15.8.2)
Requires-Dist: pycrypto (==2.6.1)
Requires-Dist: pydot (==1.0.2)
Requires-Dist: pygithub3 (==0.5.1)
Requires-Dist: pymongo (==2.8)
Requires-Dist: pypicloud-client (==5)
Requires-Dist: python-etcd (==0.4.3)
Requires-Dist: python-jenkins (==0.4.12)
Requires-Dist: quay-client (==7)
Requires-Dist: redis (==2.10.3)
Requires-Dist: requests (==2.7.0)
Requires-Dist: slacker (==0.9.21)
Requires-Dist: smart-getenv (==1.1.0)
Requires-Dist: ssh-import-id (==3.21)
